pexver/__init__.py
pexver/pexver.py
pexver-0.0.1.dist-info/LICENSE
pexver-0.0.1.dist-info/METADATA
pexver-0.0.1.dist-info/WHEEL
pexver-0.0.1.dist-info/top_level.txt
pexver-0.0.1.dist-info/RECORD
